README.rst
setup.py
ahook/__init__.py
ahook/consts.py
ahook.egg-info/PKG-INFO
ahook.egg-info/SOURCES.txt
ahook.egg-info/dependency_links.txt
ahook.egg-info/entry_points.txt
ahook.egg-info/requires.txt
ahook.egg-info/top_level.txt
ahook/hooks/__init__.py
ahook/hooks/commit_msg.py
ahook/hooks/pre_push.py