Metadata-Version: 1.0
Name: ahook
Version: 0.1.0
Summary: a collection of Git hooks
Home-page: https://github.com/akun/ahook
Author: akun
Author-email: 6awkun@gmail.com
License: MIT License
Platform: UNKNOWN
